sma_sunnyboy/__init__.py
sma_sunnyboy/key.py
sma_sunnyboy/right.py
sma_sunnyboy/sma.py
SMA_SunnyBoy-0.0.3.dist-info/LICENSE
SMA_SunnyBoy-0.0.3.dist-info/METADATA
SMA_SunnyBoy-0.0.3.dist-info/WHEEL
SMA_SunnyBoy-0.0.3.dist-info/top_level.txt
SMA_SunnyBoy-0.0.3.dist-info/RECORD
