Metadata-Version: 2.1
Name: SMA-SunnyBoy
Version: 0.0.3
Summary: A simple data retrieving for SMA SunnyBoy
Home-page: https://github.com/Dymerz/SMA-SunnyBoy
Author: Urbain Corentin
Author-email: corentin.urbain96@gmail.com
License: UNKNOWN
Platform: UNKNOWN
Classifier: Programming Language :: Python :: 3
Classifier: License :: OSI Approved :: MIT License
Classifier: Operating System :: OS Independent
Requires-Python: >=3.6
